{
  "name": "HB Codespaces",
  "dockerComposeFile": "docker-compose.yml",
  "service": "devcontainer",
  "workspaceFolder": "/workspaces/${localWorkspaceFolderBasename}",

  "postCreateCommand": "bash /workspaces/${localWorkspaceFolderBasename}/.devcontainer/aliases.sh",
  "postStartCommand": "bash /workspaces/${localWorkspaceFolderBasename}/.devcontainer/init.sh",

  "features": {
    "ghcr.io/devcontainers/features/node:1": {
      "version": "20"
    }
  },
  "customizations": {},

  "forwardPorts": [8080, 8081],
  "portsAttributes": {
    "80": {
      "onAutoForward": "ignore"
    }
  }
}